{
    "2018": [
        {"company": "A", "netAssetReturnRate": -64.9},
        {"company": "B", "netAssetReturnRate": -26.51},
        {"company": "C", "netAssetReturnRate": 1.46},
        {"company": "D", "netAssetReturnRate": null},
        {"company": "E", "netAssetReturnRate": -18.23}
    ],
    "2019": [
        {"company": "A", "netAssetReturnRate": -67.57},
        {"company": "B", "netAssetReturnRate": -31.64},
        {"company": "C", "netAssetReturnRate": 0.82},
        {"company": "D", "netAssetReturnRate": -36.98},
        {"company": "E", "netAssetReturnRate": -43.22}
    ],
    "2020": [
        {"company": "A", "netAssetReturnRate": -16.44},
        {"company": "B", "netAssetReturnRate": -0.64},
        {"company": "C", "netAssetReturnRate": 2.2},
        {"company": "D", "netAssetReturnRate": -39.58},
        {"company": "E", "netAssetReturnRate": -10.23}
    ],
    "2021": [
        {"company": "A", "netAssetReturnRate": -15.54},
        {"company": "B", "netAssetReturnRate": -0.66},
        {"company": "C", "netAssetReturnRate": 1.24},
        {"company": "D", "netAssetReturnRate": -36.27},
        {"company": "E", "netAssetReturnRate": -8.93}
    ],
    "2022": [
        {"company": "A", "netAssetReturnRate": -15.57},
        {"company": "B", "netAssetReturnRate": -2.61},
        {"company": "C", "netAssetReturnRate": 4.06},
        {"company": "D", "netAssetReturnRate": -30.96},
        {"company": "E", "netAssetReturnRate": -12.74}
    ],
    "2023": [
        {"company": "B", "netAssetReturnRate": 10.1},
        {"company": "A", "netAssetReturnRate": null},
        {"company": "C", "netAssetReturnRate": null},
        {"company": "D", "netAssetReturnRate": null},
        {"company": "E", "netAssetReturnRate": null}
    ]
}
