{
    "2018": [
        {"company": "A", "priceEarningsRatio": null},
        {"company": "B", "priceEarningsRatio": null},
        {"company": "C", "priceEarningsRatio": 54.84},
        {"company": "D", "priceEarningsRatio": null},
        {"company": "E", "priceEarningsRatio": null}
    ],
    "2019": [
        {"company": "A", "priceEarningsRatio": null},
        {"company": "B", "priceEarningsRatio": null},
        {"company": "C", "priceEarningsRatio": 95.34},
        {"company": "D", "priceEarningsRatio": null},
        {"company": "E", "priceEarningsRatio": null}
    ],
    "2020": [
        {"company": "A", "priceEarningsRatio": null},
        {"company": "B", "priceEarningsRatio": null},
        {"company": "C", "priceEarningsRatio": 132.18},
        {"company": "D", "priceEarningsRatio": null},
        {"company": "E", "priceEarningsRatio": null}
    ],
    "2021": [
        {"company": "A", "priceEarningsRatio": null},
        {"company": "B", "priceEarningsRatio": null},
        {"company": "C", "priceEarningsRatio": 252.94},
        {"company": "D", "priceEarningsRatio": null},
        {"company": "E", "priceEarningsRatio": null}
    ],
    "2022": [
        {"company": "A", "priceEarningsRatio": null},
        {"company": "B", "priceEarningsRatio": null},
        {"company": "C", "priceEarningsRatio": 45},
        {"company": "D", "priceEarningsRatio": null},
        {"company": "E", "priceEarningsRatio": null}
    ],
    "2023": [
        {"company": "B", "priceEarningsRatio": 24.07},
        {"company": "A", "priceEarningsRatio": null},
        {"company": "C", "priceEarningsRatio": null},
        {"company": "D", "priceEarningsRatio": null},
        {"company": "E", "priceEarningsRatio": null}
    ]
}
